README.md
pyproject.toml
setup.py
extract_video_frame/__init__.py
extract_video_frame/core.py
extract_video_frame.egg-info/PKG-INFO
extract_video_frame.egg-info/SOURCES.txt
extract_video_frame.egg-info/dependency_links.txt
extract_video_frame.egg-info/entry_points.txt
extract_video_frame.egg-info/requires.txt
extract_video_frame.egg-info/top_level.txt