Metadata-Version: 2.1
Name: extract-video-frame
Version: 1.0.4
Summary: extract video frame to tmp folder
Home-page: UNKNOWN
Author: ilpanda
Author-email: litencent@gmail.com
License: UNKNOWN
Platform: UNKNOWN
Requires-Python: >=3.6
